analysis/__init__.py
constrained_sdd-0.1.5.dist-info/licenses/LICENSE
sdd/__init__.py
sdd/constrained_sdd.py
tests/__init__.py
tests/test_constrained_sdd.py
constrained_sdd-0.1.5.dist-info/METADATA
constrained_sdd-0.1.5.dist-info/WHEEL
constrained_sdd-0.1.5.dist-info/top_level.txt
constrained_sdd-0.1.5.dist-info/RECORD
