Metadata-Version: 2.4
Name: constrained-sdd
Version: 0.1.5
Summary: A Python package for working with constrained Stanford Drone Dataset.
Home-page: https://github.com/april-tools/constrained-sdd
Author: Leander Kurscheidt
Classifier: Programming Language :: Python :: 3
Classifier: License :: OSI Approved :: MIT License
Classifier: Operating System :: OS Independent
Requires-Python: >=3.7
License-File: LICENSE
Requires-Dist: numpy>=2.2.4
Requires-Dist: scikit-learn>=1.6.1
Requires-Dist: pytest>=8.3.5
Requires-Dist: requests>=2.32.3
Requires-Dist: torch>=2.6.0
Dynamic: author
Dynamic: classifier
Dynamic: description
Dynamic: description-content-type
Dynamic: home-page
Dynamic: license-file
Dynamic: requires-dist
Dynamic: requires-python
Dynamic: summary
